.gitignore
LICENSE.txt
README.rst
setup.py
stdeb.cfg
demo/simple.py
demo/very_simple.py
motmot/__init__.py
motmot.cam_iface.egg-info/PKG-INFO
motmot.cam_iface.egg-info/SOURCES.txt
motmot.cam_iface.egg-info/dependency_links.txt
motmot.cam_iface.egg-info/namespace_packages.txt
motmot.cam_iface.egg-info/top_level.txt
motmot/cam_iface/__init__.py
motmot/cam_iface/cam_iface_ctypes.py
motmot/cam_iface/choose.py