Metadata-Version: 1.0
Name: motmot.cam-iface
Version: 0.5.5
Summary: cross-platform, cross-backend camera driver
Home-page: http://code.astraw.com/projects/motmot/cam_iface.html
Author: Andrew Straw
Author-email: strawman@astraw.com
License: BSD
Platform: UNKNOWN
